LICENSE
MANIFEST.in
README.rst
setup.py
trac_fedmsg_plugin.py
trac_fedmsg_plugin.egg-info/PKG-INFO
trac_fedmsg_plugin.egg-info/SOURCES.txt
trac_fedmsg_plugin.egg-info/dependency_links.txt
trac_fedmsg_plugin.egg-info/entry_points.txt
trac_fedmsg_plugin.egg-info/top_level.txt