Metadata-Version: 1.0
Name: trac-fedmsg-plugin
Version: 0.1.0
Summary: Emit fedmsg messages
Home-page: http://github.com/fedora-infra/trac-fedmsg-plugin
Author: Ralph Bean
Author-email: rbean@redhat.com
License: MIT
Platform: UNKNOWN
